MANIFEST.in
README.md
README.rst
setup.py
jcaptcha/SliderCaptcha.py
jcaptcha/VerificationCode.py
jcaptcha/__init__.py
jcaptcha.egg-info/PKG-INFO
jcaptcha.egg-info/SOURCES.txt
jcaptcha.egg-info/dependency_links.txt
jcaptcha.egg-info/not-zip-safe
jcaptcha.egg-info/requires.txt
jcaptcha.egg-info/top_level.txt
jcaptcha/data/SIMYOU.TTF