Metadata-Version: 1.0
Name: jcaptcha
Version: 1.0.6
Summary: 验证码生成
Home-page: https://github.com/xiaofeng283/jcaptcha
Author: Jervon
Author-email: xiaofeng283@gmail.com
License: MIT
Platform: UNKNOWN
